[
  {
    "event_id": "330",
    "order_no": "EM26032300069178",
    "old_status": null,
    "new_status": "pending",
    "operator_id": 31,
    "operator_type": "user",
    "reason": "用户兑换商品",
    "metadata": {
      "sku_id": 7,
      "quantity": 1,
      "pay_amount": 100,
      "minted_item_id": 39809,
      "exchange_item_id": 7
    },
    "idempotency_key": "order_event_EM1774200895192OAUSXJ_pending_31_1774200895",
    "created_at": "2026-03-23 01:34:55"
  },
  {
    "event_id": "331",
    "order_no": "EM260323000692FE",
    "old_status": null,
    "new_status": "pending",
    "operator_id": 31,
    "operator_type": "user",
    "reason": "用户兑换商品",
    "metadata": {
      "sku_id": 7,
      "quantity": 1,
      "pay_amount": 100,
      "minted_item_id": 39810,
      "exchange_item_id": 7
    },
    "idempotency_key": "order_event_EM1774201431234XEXT9K_pending_31_1774201431",
    "created_at": "2026-03-23 01:43:51"
  },
  {
    "event_id": "338",
    "order_no": "EM26032300069933",
    "old_status": null,
    "new_status": "pending",
    "operator_id": 32,
    "operator_type": "user",
    "reason": "用户兑换商品",
    "metadata": {
      "sku_id": "116",
      "quantity": 1,
      "pay_amount": 100,
      "minted_item_id": null,
      "exchange_item_id": "248"
    },
    "idempotency_key": "order_event_EM26032300069933_pending_32_1774224349",
    "created_at": "2026-03-23 08:05:49"
  },
  {
    "event_id": "356",
    "order_no": "EM260323000717D4",
    "old_status": null,
    "new_status": "pending",
    "operator_id": 32,
    "operator_type": "user",
    "reason": "用户兑换商品",
    "metadata": {
      "sku_id": "116",
      "quantity": 1,
      "pay_amount": 100,
      "minted_item_id": null,
      "exchange_item_id": "248"
    },
    "idempotency_key": "order_event_EM260323000717D4_pending_32_1774225255",
    "created_at": "2026-03-23 08:20:55"
  },
  {
    "event_id": "357",
    "order_no": "EM26032300071846",
    "old_status": null,
    "new_status": "pending",
    "operator_id": 32,
    "operator_type": "user",
    "reason": "用户兑换商品",
    "metadata": {
      "sku_id": "116",
      "quantity": 1,
      "pay_amount": 100,
      "minted_item_id": null,
      "exchange_item_id": "248"
    },
    "idempotency_key": "order_event_EM26032300071846_pending_32_1774225337",
    "created_at": "2026-03-23 08:22:17"
  },
  {
    "event_id": "358",
    "order_no": "EM26032300071962",
    "old_status": null,
    "new_status": "pending",
    "operator_id": 32,
    "operator_type": "user",
    "reason": "用户兑换商品",
    "metadata": {
      "sku_id": "116",
      "quantity": 1,
      "pay_amount": 100,
      "minted_item_id": null,
      "exchange_item_id": "248"
    },
    "idempotency_key": "order_event_EM26032300071962_pending_32_1774225344",
    "created_at": "2026-03-23 08:22:24"
  },
  {
    "event_id": "380",
    "order_no": "EM260323000741CE",
    "old_status": null,
    "new_status": "pending",
    "operator_id": 32,
    "operator_type": "user",
    "reason": "用户兑换商品",
    "metadata": {
      "sku_id": "116",
      "quantity": 1,
      "pay_amount": 100,
      "minted_item_id": null,
      "exchange_item_id": "248"
    },
    "idempotency_key": "order_event_EM260323000741CE_pending_32_1774225870",
    "created_at": "2026-03-23 08:31:10"
  },
  {
    "event_id": "409",
    "order_no": "EM260323000770B6",
    "old_status": null,
    "new_status": "pending",
    "operator_id": 32,
    "operator_type": "user",
    "reason": "用户兑换商品",
    "metadata": {
      "sku_id": "116",
      "quantity": 1,
      "pay_amount": 100,
      "minted_item_id": null,
      "exchange_item_id": "248"
    },
    "idempotency_key": "order_event_EM260323000770B6_pending_32_1774226587",
    "created_at": "2026-03-23 08:43:07"
  },
  {
    "event_id": "417",
    "order_no": "EM260323000778FA",
    "old_status": null,
    "new_status": "pending",
    "operator_id": 32,
    "operator_type": "user",
    "reason": "用户兑换商品",
    "metadata": {
      "sku_id": "116",
      "quantity": 1,
      "pay_amount": 100,
      "minted_item_id": null,
      "exchange_item_id": "248"
    },
    "idempotency_key": "order_event_EM260323000778FA_pending_32_1774229689",
    "created_at": "2026-03-23 09:34:49"
  },
  {
    "event_id": "432",
    "order_no": "EM260323000793FF",
    "old_status": null,
    "new_status": "pending",
    "operator_id": 32,
    "operator_type": "user",
    "reason": "用户兑换商品",
    "metadata": {
      "sku_id": "116",
      "quantity": 1,
      "pay_amount": 100,
      "minted_item_id": null,
      "exchange_item_id": "248"
    },
    "idempotency_key": "order_event_EM260323000793FF_pending_32_1774229886",
    "created_at": "2026-03-23 09:38:06"
  },
  {
    "event_id": "454",
    "order_no": "EM260323000815A7",
    "old_status": null,
    "new_status": "pending",
    "operator_id": 32,
    "operator_type": "user",
    "reason": "用户兑换商品",
    "metadata": {
      "sku_id": "116",
      "quantity": 1,
      "pay_amount": 100,
      "minted_item_id": null,
      "exchange_item_id": "248"
    },
    "idempotency_key": "order_event_EM260323000815A7_pending_32_1774230271",
    "created_at": "2026-03-23 09:44:31"
  },
  {
    "event_id": "462",
    "order_no": "EM260324000823A6",
    "old_status": null,
    "new_status": "pending",
    "operator_id": 32,
    "operator_type": "user",
    "reason": "用户兑换商品",
    "metadata": {
      "sku_id": "116",
      "quantity": 1,
      "pay_amount": 100,
      "minted_item_id": null,
      "exchange_item_id": "248"
    },
    "idempotency_key": "order_event_EM260324000823A6_pending_32_1774288812",
    "created_at": "2026-03-24 02:00:12"
  },
  {
    "event_id": "484",
    "order_no": "EM26032400084563",
    "old_status": null,
    "new_status": "pending",
    "operator_id": 32,
    "operator_type": "user",
    "reason": "用户兑换商品",
    "metadata": {
      "sku_id": "116",
      "quantity": 1,
      "pay_amount": 100,
      "minted_item_id": null,
      "exchange_item_id": "248"
    },
    "idempotency_key": "order_event_EM26032400084563_pending_32_1774289961",
    "created_at": "2026-03-24 02:19:21"
  },
  {
    "event_id": "492",
    "order_no": "EM260324000853F9",
    "old_status": null,
    "new_status": "pending",
    "operator_id": 32,
    "operator_type": "user",
    "reason": "用户兑换商品",
    "metadata": {
      "sku_id": "116",
      "quantity": 1,
      "pay_amount": 100,
      "minted_item_id": null,
      "exchange_item_id": "248"
    },
    "idempotency_key": "order_event_EM260324000853F9_pending_32_1774298160",
    "created_at": "2026-03-24 04:36:00"
  },
  {
    "event_id": "500",
    "order_no": "EM2603240008612C",
    "old_status": null,
    "new_status": "pending",
    "operator_id": 32,
    "operator_type": "user",
    "reason": "用户兑换商品",
    "metadata": {
      "sku_id": "116",
      "quantity": 1,
      "pay_amount": 100,
      "minted_item_id": null,
      "exchange_item_id": "248"
    },
    "idempotency_key": "order_event_EM2603240008612C_pending_32_1774298226",
    "created_at": "2026-03-24 04:37:06"
  },
  {
    "event_id": "508",
    "order_no": "EM260324000869C5",
    "old_status": null,
    "new_status": "pending",
    "operator_id": 32,
    "operator_type": "user",
    "reason": "用户兑换商品",
    "metadata": {
      "sku_id": "116",
      "quantity": 1,
      "pay_amount": 100,
      "minted_item_id": null,
      "exchange_item_id": "248"
    },
    "idempotency_key": "order_event_EM260324000869C5_pending_32_1774298250",
    "created_at": "2026-03-24 04:37:30"
  },
  {
    "event_id": "516",
    "order_no": "EM260324000877BA",
    "old_status": null,
    "new_status": "pending",
    "operator_id": 32,
    "operator_type": "user",
    "reason": "用户兑换商品",
    "metadata": {
      "sku_id": "116",
      "quantity": 1,
      "pay_amount": 100,
      "minted_item_id": null,
      "exchange_item_id": "248"
    },
    "idempotency_key": "order_event_EM260324000877BA_pending_32_1774298307",
    "created_at": "2026-03-24 04:38:27"
  },
  {
    "event_id": "524",
    "order_no": "EM2603240008859E",
    "old_status": null,
    "new_status": "pending",
    "operator_id": 32,
    "operator_type": "user",
    "reason": "用户兑换商品",
    "metadata": {
      "sku_id": "116",
      "quantity": 1,
      "pay_amount": 100,
      "minted_item_id": null,
      "exchange_item_id": "248"
    },
    "idempotency_key": "order_event_EM2603240008859E_pending_32_1774298337",
    "created_at": "2026-03-24 04:38:57"
  },
  {
    "event_id": "539",
    "order_no": "EM2603240009001F",
    "old_status": null,
    "new_status": "pending",
    "operator_id": 32,
    "operator_type": "user",
    "reason": "用户兑换商品",
    "metadata": {
      "sku_id": "116",
      "quantity": 1,
      "pay_amount": 100,
      "minted_item_id": null,
      "exchange_item_id": "248"
    },
    "idempotency_key": "order_event_EM2603240009001F_pending_32_1774298661",
    "created_at": "2026-03-24 04:44:21"
  },
  {
    "event_id": "540",
    "order_no": "EM260324000901A9",
    "old_status": null,
    "new_status": "pending",
    "operator_id": 32,
    "operator_type": "user",
    "reason": "用户兑换商品",
    "metadata": {
      "sku_id": "116",
      "quantity": 1,
      "pay_amount": 100,
      "minted_item_id": null,
      "exchange_item_id": "248"
    },
    "idempotency_key": "order_event_EM260324000901A9_pending_32_1774298675",
    "created_at": "2026-03-24 04:44:35"
  },
  {
    "event_id": "548",
    "order_no": "EM260324000909A0",
    "old_status": null,
    "new_status": "pending",
    "operator_id": 32,
    "operator_type": "user",
    "reason": "用户兑换商品",
    "metadata": {
      "sku_id": "116",
      "quantity": 1,
      "pay_amount": 100,
      "minted_item_id": null,
      "exchange_item_id": "248"
    },
    "idempotency_key": "order_event_EM260324000909A0_pending_32_1774299584",
    "created_at": "2026-03-24 04:59:44"
  },
  {
    "event_id": "556",
    "order_no": "EM26032400091794",
    "old_status": null,
    "new_status": "pending",
    "operator_id": 32,
    "operator_type": "user",
    "reason": "用户兑换商品",
    "metadata": {
      "sku_id": "116",
      "quantity": 1,
      "pay_amount": 100,
      "minted_item_id": null,
      "exchange_item_id": "248"
    },
    "idempotency_key": "order_event_EM26032400091794_pending_32_1774300571",
    "created_at": "2026-03-24 05:16:11"
  },
  {
    "event_id": "557",
    "order_no": "EM26032400091794",
    "old_status": "pending",
    "new_status": "approved",
    "operator_id": 31,
    "operator_type": "admin",
    "reason": "测试审核通过",
    "metadata": null,
    "idempotency_key": "order_event_EM26032400091794_approved_31_1774369222",
    "created_at": "2026-03-25 00:20:22"
  },
  {
    "event_id": "558",
    "order_no": "EM26032400091794",
    "old_status": "approved",
    "new_status": "shipped",
    "operator_id": 31,
    "operator_type": "admin",
    "reason": "测试发货",
    "metadata": null,
    "idempotency_key": "order_event_EM26032400091794_shipped_31_1774369222",
    "created_at": "2026-03-25 00:20:22"
  },
  {
    "event_id": "559",
    "order_no": "EM26032400091794",
    "old_status": "shipped",
    "new_status": "completed",
    "operator_id": 31,
    "operator_type": "admin",
    "reason": "测试完成",
    "metadata": null,
    "idempotency_key": "order_event_EM26032400091794_completed_31_1774369222",
    "created_at": "2026-03-25 00:20:22"
  },
  {
    "event_id": "567",
    "order_no": "EM26032500092596",
    "old_status": null,
    "new_status": "pending",
    "operator_id": 32,
    "operator_type": "user",
    "reason": "用户兑换商品",
    "metadata": {
      "sku_id": "116",
      "quantity": 1,
      "pay_amount": 100,
      "minted_item_id": null,
      "exchange_item_id": "248"
    },
    "idempotency_key": "order_event_EM26032500092596_pending_32_1774380884",
    "created_at": "2026-03-25 03:34:44"
  },
  {
    "event_id": "568",
    "order_no": "EM26040200092699",
    "old_status": null,
    "new_status": "pending",
    "operator_id": 32,
    "operator_type": "user",
    "reason": "用户兑换商品",
    "metadata": {
      "sku_id": "116",
      "quantity": 1,
      "pay_amount": 100,
      "minted_item_id": null,
      "exchange_item_id": "248"
    },
    "idempotency_key": "order_event_EM26040200092699_pending_32_1775083748",
    "created_at": "2026-04-02 06:49:08"
  },
  {
    "event_id": "569",
    "order_no": "EM26040200092769",
    "old_status": null,
    "new_status": "pending",
    "operator_id": 32,
    "operator_type": "user",
    "reason": "用户兑换商品",
    "metadata": {
      "sku_id": "116",
      "quantity": 1,
      "pay_amount": 100,
      "minted_item_id": null,
      "exchange_item_id": "248"
    },
    "idempotency_key": "order_event_EM26040200092769_pending_32_1775084660",
    "created_at": "2026-04-02 07:04:20"
  },
  {
    "event_id": "570",
    "order_no": "EM26040800092846",
    "old_status": null,
    "new_status": "pending",
    "operator_id": 32,
    "operator_type": "user",
    "reason": "用户兑换商品",
    "metadata": {
      "sku_id": "116",
      "quantity": 1,
      "pay_amount": 100,
      "minted_item_id": null,
      "exchange_item_id": "248"
    },
    "idempotency_key": "order_event_EM26040800092846_pending_32_1775596233",
    "created_at": "2026-04-08 05:10:33"
  },
  {
    "event_id": "578",
    "order_no": "EM2604100009398B",
    "old_status": null,
    "new_status": "pending",
    "operator_id": 32,
    "operator_type": "user",
    "reason": "用户兑换商品",
    "metadata": {
      "sku_id": "116",
      "quantity": 1,
      "pay_amount": 100,
      "minted_item_id": null,
      "exchange_item_id": "248"
    },
    "idempotency_key": "order_event_EM2604100009398B_pending_32_1775774240",
    "created_at": "2026-04-10 06:37:20"
  },
  {
    "event_id": "593",
    "order_no": "EM260422000954AF",
    "old_status": null,
    "new_status": "pending",
    "operator_id": 32,
    "operator_type": "user",
    "reason": "用户兑换商品",
    "metadata": {
      "sku_id": "116",
      "quantity": 1,
      "pay_amount": 100,
      "minted_item_id": null,
      "exchange_item_id": "248"
    },
    "idempotency_key": "order_event_EM260422000954AF_pending_32_1776827515",
    "created_at": "2026-04-22 11:11:55"
  },
  {
    "event_id": "601",
    "order_no": "EM26042200096248",
    "old_status": null,
    "new_status": "pending",
    "operator_id": 32,
    "operator_type": "user",
    "reason": "用户兑换商品",
    "metadata": {
      "sku_id": "116",
      "quantity": 1,
      "pay_amount": 100,
      "minted_item_id": null,
      "exchange_item_id": "248"
    },
    "idempotency_key": "order_event_EM26042200096248_pending_32_1776827600",
    "created_at": "2026-04-22 11:13:20"
  },
  {
    "event_id": "609",
    "order_no": "EM2604220009704F",
    "old_status": null,
    "new_status": "pending",
    "operator_id": 32,
    "operator_type": "user",
    "reason": "用户兑换商品",
    "metadata": {
      "sku_id": "116",
      "quantity": 1,
      "pay_amount": 100,
      "minted_item_id": null,
      "exchange_item_id": "248"
    },
    "idempotency_key": "order_event_EM2604220009704F_pending_32_1776829149",
    "created_at": "2026-04-22 11:39:09"
  },
  {
    "event_id": "617",
    "order_no": "EM260422000978B1",
    "old_status": null,
    "new_status": "pending",
    "operator_id": 32,
    "operator_type": "user",
    "reason": "用户兑换商品",
    "metadata": {
      "sku_id": "116",
      "quantity": 1,
      "pay_amount": 100,
      "minted_item_id": null,
      "exchange_item_id": "248"
    },
    "idempotency_key": "order_event_EM260422000978B1_pending_32_1776829309",
    "created_at": "2026-04-22 11:41:49"
  },
  {
    "event_id": "625",
    "order_no": "EM26042300098609",
    "old_status": null,
    "new_status": "pending",
    "operator_id": 32,
    "operator_type": "user",
    "reason": "用户兑换商品",
    "metadata": {
      "sku_id": "116",
      "quantity": 1,
      "pay_amount": 100,
      "minted_item_id": null,
      "exchange_item_id": "248"
    },
    "idempotency_key": "order_event_EM26042300098609_pending_32_1776874776",
    "created_at": "2026-04-23 00:19:36"
  },
  {
    "event_id": "633",
    "order_no": "EM260423000994A5",
    "old_status": null,
    "new_status": "pending",
    "operator_id": 32,
    "operator_type": "user",
    "reason": "用户兑换商品",
    "metadata": {
      "sku_id": "116",
      "quantity": 1,
      "pay_amount": 100,
      "minted_item_id": null,
      "exchange_item_id": "248"
    },
    "idempotency_key": "order_event_EM260423000994A5_pending_32_1776883914",
    "created_at": "2026-04-23 02:51:54"
  },
  {
    "event_id": "641",
    "order_no": "EM26042300100225",
    "old_status": null,
    "new_status": "pending",
    "operator_id": 32,
    "operator_type": "user",
    "reason": "用户兑换商品",
    "metadata": {
      "sku_id": "116",
      "quantity": 1,
      "pay_amount": 100,
      "minted_item_id": null,
      "exchange_item_id": "248"
    },
    "idempotency_key": "order_event_EM26042300100225_pending_32_1776884138",
    "created_at": "2026-04-23 02:55:38"
  },
  {
    "event_id": "649",
    "order_no": "EM26042300101099",
    "old_status": null,
    "new_status": "pending",
    "operator_id": 32,
    "operator_type": "user",
    "reason": "用户兑换商品",
    "metadata": {
      "sku_id": "116",
      "quantity": 1,
      "pay_amount": 100,
      "minted_item_id": null,
      "exchange_item_id": "248"
    },
    "idempotency_key": "order_event_EM26042300101099_pending_32_1776884350",
    "created_at": "2026-04-23 02:59:10"
  },
  {
    "event_id": "650",
    "order_no": "EM260424001011EB",
    "old_status": null,
    "new_status": "pending",
    "operator_id": 32,
    "operator_type": "user",
    "reason": "用户兑换商品",
    "metadata": {
      "sku_id": "116",
      "quantity": 1,
      "pay_amount": 100,
      "minted_item_id": null,
      "exchange_item_id": "248"
    },
    "idempotency_key": "order_event_EM260424001011EB_pending_32_1776972976",
    "created_at": "2026-04-24 03:36:16"
  },
  {
    "event_id": "665",
    "order_no": "EM2604240010268A",
    "old_status": null,
    "new_status": "pending",
    "operator_id": 32,
    "operator_type": "user",
    "reason": "用户兑换商品",
    "metadata": {
      "sku_id": "116",
      "quantity": 1,
      "pay_amount": 100,
      "minted_item_id": null,
      "exchange_item_id": "248"
    },
    "idempotency_key": "order_event_EM2604240010268A_pending_32_1776987117",
    "created_at": "2026-04-24 07:31:57"
  },
  {
    "event_id": "673",
    "order_no": "EM2604240010345B",
    "old_status": null,
    "new_status": "pending",
    "operator_id": 32,
    "operator_type": "user",
    "reason": "用户兑换商品",
    "metadata": {
      "sku_id": "116",
      "quantity": 1,
      "pay_amount": 100,
      "minted_item_id": null,
      "exchange_item_id": "248"
    },
    "idempotency_key": "order_event_EM2604240010345B_pending_32_1776987214",
    "created_at": "2026-04-24 07:33:34"
  },
  {
    "event_id": "681",
    "order_no": "EM26042400104234",
    "old_status": null,
    "new_status": "pending",
    "operator_id": 32,
    "operator_type": "user",
    "reason": "用户兑换商品",
    "metadata": {
      "sku_id": "116",
      "quantity": 1,
      "pay_amount": 100,
      "minted_item_id": null,
      "exchange_item_id": "248"
    },
    "idempotency_key": "order_event_EM26042400104234_pending_32_1776987632",
    "created_at": "2026-04-24 07:40:32"
  },
  {
    "event_id": "689",
    "order_no": "EM26042500105057",
    "old_status": null,
    "new_status": "pending",
    "operator_id": 32,
    "operator_type": "user",
    "reason": "用户兑换商品",
    "metadata": {
      "sku_id": "116",
      "quantity": 1,
      "pay_amount": 100,
      "minted_item_id": null,
      "exchange_item_id": "248"
    },
    "idempotency_key": "order_event_EM26042500105057_pending_32_1777066883",
    "created_at": "2026-04-25 05:41:23"
  },
  {
    "event_id": "697",
    "order_no": "EM26042500105825",
    "old_status": null,
    "new_status": "pending",
    "operator_id": 32,
    "operator_type": "user",
    "reason": "用户兑换商品",
    "metadata": {
      "sku_id": "116",
      "quantity": 1,
      "pay_amount": 100,
      "minted_item_id": null,
      "exchange_item_id": "248"
    },
    "idempotency_key": "order_event_EM26042500105825_pending_32_1777068487",
    "created_at": "2026-04-25 06:08:07"
  },
  {
    "event_id": "698",
    "order_no": "EM260425001059D1",
    "old_status": null,
    "new_status": "pending",
    "operator_id": 32,
    "operator_type": "user",
    "reason": "用户兑换商品",
    "metadata": {
      "sku_id": "116",
      "quantity": 1,
      "pay_amount": 100,
      "minted_item_id": null,
      "exchange_item_id": "248"
    },
    "idempotency_key": "order_event_EM260425001059D1_pending_32_1777069922",
    "created_at": "2026-04-25 06:32:02"
  },
  {
    "event_id": "706",
    "order_no": "EM26042500106785",
    "old_status": null,
    "new_status": "pending",
    "operator_id": 32,
    "operator_type": "user",
    "reason": "用户兑换商品",
    "metadata": {
      "sku_id": "116",
      "quantity": 1,
      "pay_amount": 100,
      "minted_item_id": null,
      "exchange_item_id": "248"
    },
    "idempotency_key": "order_event_EM26042500106785_pending_32_1777070499",
    "created_at": "2026-04-25 06:41:39"
  },
  {
    "event_id": "714",
    "order_no": "EM2604250010753F",
    "old_status": null,
    "new_status": "pending",
    "operator_id": 32,
    "operator_type": "user",
    "reason": "用户兑换商品",
    "metadata": {
      "sku_id": "116",
      "quantity": 1,
      "pay_amount": 100,
      "minted_item_id": null,
      "exchange_item_id": "248"
    },
    "idempotency_key": "order_event_EM2604250010753F_pending_32_1777071185",
    "created_at": "2026-04-25 06:53:05"
  },
  {
    "event_id": "722",
    "order_no": "EM2604250010837D",
    "old_status": null,
    "new_status": "pending",
    "operator_id": 32,
    "operator_type": "user",
    "reason": "用户兑换商品",
    "metadata": {
      "sku_id": "116",
      "quantity": 1,
      "pay_amount": 100,
      "minted_item_id": null,
      "exchange_item_id": "248"
    },
    "idempotency_key": "order_event_EM2604250010837D_pending_32_1777071285",
    "created_at": "2026-04-25 06:54:45"
  },
  {
    "event_id": "730",
    "order_no": "EM2604250010916C",
    "old_status": null,
    "new_status": "pending",
    "operator_id": 32,
    "operator_type": "user",
    "reason": "用户兑换商品",
    "metadata": {
      "sku_id": "116",
      "quantity": 1,
      "pay_amount": 100,
      "minted_item_id": null,
      "exchange_item_id": "248"
    },
    "idempotency_key": "order_event_EM2604250010916C_pending_32_1777079120",
    "created_at": "2026-04-25 09:05:20"
  },
  {
    "event_id": "738",
    "order_no": "EM26052600109994",
    "old_status": null,
    "new_status": "pending",
    "operator_id": 32,
    "operator_type": "user",
    "reason": "用户兑换商品",
    "metadata": {
      "sku_id": "116",
      "quantity": 1,
      "pay_amount": 100,
      "minted_item_id": null,
      "exchange_item_id": "248"
    },
    "idempotency_key": "order_event_EM26052600109994_pending_32_1779738469",
    "created_at": "2026-05-26 03:47:49"
  },
  {
    "event_id": "746",
    "order_no": "EM2606030011076A",
    "old_status": null,
    "new_status": "pending",
    "operator_id": 32,
    "operator_type": "user",
    "reason": "用户兑换商品",
    "metadata": {
      "sku_id": "116",
      "quantity": 1,
      "pay_amount": 100,
      "minted_item_id": null,
      "exchange_item_id": "248"
    },
    "idempotency_key": "order_event_EM2606030011076A_pending_32_1780416890",
    "created_at": "2026-06-03 00:14:50"
  },
  {
    "event_id": "754",
    "order_no": "EM26060300111578",
    "old_status": null,
    "new_status": "pending",
    "operator_id": 32,
    "operator_type": "user",
    "reason": "用户兑换商品",
    "metadata": {
      "sku_id": "116",
      "quantity": 1,
      "pay_amount": 100,
      "minted_item_id": null,
      "exchange_item_id": "248"
    },
    "idempotency_key": "order_event_EM26060300111578_pending_32_1780421598",
    "created_at": "2026-06-03 01:33:18"
  },
  {
    "event_id": "762",
    "order_no": "EM260603001123D0",
    "old_status": null,
    "new_status": "pending",
    "operator_id": 32,
    "operator_type": "user",
    "reason": "用户兑换商品",
    "metadata": {
      "sku_id": "116",
      "quantity": 1,
      "pay_amount": 100,
      "minted_item_id": null,
      "exchange_item_id": "248"
    },
    "idempotency_key": "order_event_EM260603001123D0_pending_32_1780422132",
    "created_at": "2026-06-03 01:42:12"
  },
  {
    "event_id": "770",
    "order_no": "EM260603001131EC",
    "old_status": null,
    "new_status": "pending",
    "operator_id": 32,
    "operator_type": "user",
    "reason": "用户兑换商品",
    "metadata": {
      "sku_id": "116",
      "quantity": 1,
      "pay_amount": 100,
      "minted_item_id": null,
      "exchange_item_id": "248"
    },
    "idempotency_key": "order_event_EM260603001131EC_pending_32_1780424064",
    "created_at": "2026-06-03 02:14:24"
  },
  {
    "event_id": "778",
    "order_no": "EM26060300113952",
    "old_status": null,
    "new_status": "pending",
    "operator_id": 32,
    "operator_type": "user",
    "reason": "用户兑换商品",
    "metadata": {
      "sku_id": "116",
      "quantity": 1,
      "pay_amount": 100,
      "minted_item_id": null,
      "exchange_item_id": "248"
    },
    "idempotency_key": "order_event_EM26060300113952_pending_32_1780426835",
    "created_at": "2026-06-03 03:00:35"
  },
  {
    "event_id": "786",
    "order_no": "EM26060300114749",
    "old_status": null,
    "new_status": "pending",
    "operator_id": 32,
    "operator_type": "user",
    "reason": "用户兑换商品",
    "metadata": {
      "sku_id": "116",
      "quantity": 1,
      "pay_amount": 100,
      "minted_item_id": null,
      "exchange_item_id": "248"
    },
    "idempotency_key": "order_event_EM26060300114749_pending_32_1780427396",
    "created_at": "2026-06-03 03:09:56"
  },
  {
    "event_id": "794",
    "order_no": "EM260603001155BC",
    "old_status": null,
    "new_status": "pending",
    "operator_id": 32,
    "operator_type": "user",
    "reason": "用户兑换商品",
    "metadata": {
      "sku_id": "116",
      "quantity": 1,
      "pay_amount": 100,
      "minted_item_id": null,
      "exchange_item_id": "248"
    },
    "idempotency_key": "order_event_EM260603001155BC_pending_32_1780428687",
    "created_at": "2026-06-03 03:31:27"
  },
  {
    "event_id": "801",
    "order_no": "EM260603001162A5",
    "old_status": null,
    "new_status": "pending",
    "operator_id": 32,
    "operator_type": "user",
    "reason": "用户兑换商品",
    "metadata": {
      "sku_id": "116",
      "quantity": 1,
      "pay_amount": 100,
      "minted_item_id": null,
      "exchange_item_id": "248"
    },
    "idempotency_key": "order_event_EM260603001162A5_pending_32_1780428973",
    "created_at": "2026-06-03 03:36:13"
  },
  {
    "event_id": "858",
    "order_no": "EM26061200121994",
    "old_status": null,
    "new_status": "pending",
    "operator_id": 31,
    "operator_type": "user",
    "reason": "用户兑换商品",
    "metadata": {
      "sku_id": 6,
      "quantity": 1,
      "pay_amount": 10,
      "is_prop_order": false,
      "minted_item_id": 45243,
      "exchange_item_id": 6
    },
    "idempotency_key": "order_event_EM26061200121994_pending_31_1781218311",
    "created_at": "2026-06-12 06:51:51"
  },
  {
    "event_id": "859",
    "order_no": "EM260612001220D6",
    "old_status": null,
    "new_status": "pending",
    "operator_id": 31,
    "operator_type": "user",
    "reason": "用户兑换商品",
    "metadata": {
      "sku_id": 6,
      "quantity": 1,
      "pay_amount": 10,
      "is_prop_order": false,
      "minted_item_id": 45244,
      "exchange_item_id": 6
    },
    "idempotency_key": "order_event_EM260612001220D6_pending_31_1781218321",
    "created_at": "2026-06-12 06:52:01"
  },
  {
    "event_id": "860",
    "order_no": "EM26061200122131",
    "old_status": null,
    "new_status": "pending",
    "operator_id": 31,
    "operator_type": "user",
    "reason": "用户兑换商品",
    "metadata": {
      "sku_id": 6,
      "quantity": 1,
      "pay_amount": 10,
      "is_prop_order": false,
      "minted_item_id": 45245,
      "exchange_item_id": 6
    },
    "idempotency_key": "order_event_EM26061200122131_pending_31_1781218325",
    "created_at": "2026-06-12 06:52:05"
  },
  {
    "event_id": "861",
    "order_no": "EM26061200122242",
    "old_status": null,
    "new_status": "pending",
    "operator_id": 31,
    "operator_type": "user",
    "reason": "用户兑换商品",
    "metadata": {
      "sku_id": 6,
      "quantity": 1,
      "pay_amount": 10,
      "is_prop_order": false,
      "minted_item_id": 45246,
      "exchange_item_id": 6
    },
    "idempotency_key": "order_event_EM26061200122242_pending_31_1781271701",
    "created_at": "2026-06-12 21:41:41"
  },
  {
    "event_id": "862",
    "order_no": "EM260612001223CD",
    "old_status": null,
    "new_status": "pending",
    "operator_id": 31,
    "operator_type": "user",
    "reason": "用户兑换商品",
    "metadata": {
      "sku_id": 6,
      "quantity": 1,
      "pay_amount": 10,
      "is_prop_order": false,
      "minted_item_id": 45247,
      "exchange_item_id": 6
    },
    "idempotency_key": "order_event_EM260612001223CD_pending_31_1781271756",
    "created_at": "2026-06-12 21:42:36"
  },
  {
    "event_id": "863",
    "order_no": "EM26061200122432",
    "old_status": null,
    "new_status": "pending",
    "operator_id": 31,
    "operator_type": "user",
    "reason": "用户兑换商品",
    "metadata": {
      "sku_id": 6,
      "quantity": 1,
      "pay_amount": 10,
      "is_prop_order": false,
      "minted_item_id": 45248,
      "exchange_item_id": 6
    },
    "idempotency_key": "order_event_EM26061200122432_pending_31_1781272410",
    "created_at": "2026-06-12 21:53:30"
  },
  {
    "event_id": "864",
    "order_no": "EM2606120012250D",
    "old_status": null,
    "new_status": "pending",
    "operator_id": 31,
    "operator_type": "user",
    "reason": "用户兑换商品",
    "metadata": {
      "sku_id": 6,
      "quantity": 1,
      "pay_amount": 10,
      "is_prop_order": false,
      "minted_item_id": 45249,
      "exchange_item_id": 6
    },
    "idempotency_key": "order_event_EM2606120012250D_pending_31_1781272420",
    "created_at": "2026-06-12 21:53:40"
  },
  {
    "event_id": "865",
    "order_no": "EM26061200122636",
    "old_status": null,
    "new_status": "pending",
    "operator_id": 31,
    "operator_type": "user",
    "reason": "用户兑换商品",
    "metadata": {
      "sku_id": 6,
      "quantity": 1,
      "pay_amount": 10,
      "is_prop_order": false,
      "minted_item_id": 45250,
      "exchange_item_id": 6
    },
    "idempotency_key": "order_event_EM26061200122636_pending_31_1781272817",
    "created_at": "2026-06-12 22:00:17"
  },
  {
    "event_id": "866",
    "order_no": "EM2606120012273D",
    "old_status": null,
    "new_status": "pending",
    "operator_id": 31,
    "operator_type": "user",
    "reason": "用户兑换商品",
    "metadata": {
      "sku_id": 6,
      "quantity": 1,
      "pay_amount": 10,
      "is_prop_order": false,
      "minted_item_id": 45251,
      "exchange_item_id": 6
    },
    "idempotency_key": "order_event_EM2606120012273D_pending_31_1781273029",
    "created_at": "2026-06-12 22:03:49"
  },
  {
    "event_id": "867",
    "order_no": "EM26061300122845",
    "old_status": null,
    "new_status": "completed",
    "operator_id": 31,
    "operator_type": "user",
    "reason": "用户购买虚拟道具（即时完成）",
    "metadata": {
      "sku_id": 401,
      "quantity": 1,
      "pay_amount": 500,
      "is_prop_order": true,
      "minted_item_id": 45252,
      "exchange_item_id": 535
    },
    "idempotency_key": "order_event_EM26061300122845_completed_31_1781284636",
    "created_at": "2026-06-13 01:17:16"
  },
  {
    "event_id": "868",
    "order_no": "EM260613001229E2",
    "old_status": null,
    "new_status": "completed",
    "operator_id": 31,
    "operator_type": "user",
    "reason": "用户购买虚拟道具（即时完成）",
    "metadata": {
      "sku_id": 401,
      "quantity": 1,
      "pay_amount": 500,
      "is_prop_order": true,
      "minted_item_id": 45253,
      "exchange_item_id": 535
    },
    "idempotency_key": "order_event_EM260613001229E2_completed_31_1781284744",
    "created_at": "2026-06-13 01:19:04"
  },
  {
    "event_id": "869",
    "order_no": "EM260613001230A6",
    "old_status": null,
    "new_status": "completed",
    "operator_id": 31,
    "operator_type": "user",
    "reason": "用户购买虚拟道具（即时完成）",
    "metadata": {
      "sku_id": 403,
      "quantity": 1,
      "pay_amount": 50,
      "is_prop_order": true,
      "minted_item_id": 45254,
      "exchange_item_id": 537
    },
    "idempotency_key": "order_event_EM260613001230A6_completed_31_1781290206",
    "created_at": "2026-06-13 02:50:06"
  },
  {
    "event_id": "870",
    "order_no": "EM260613001231F2",
    "old_status": null,
    "new_status": "completed",
    "operator_id": 31,
    "operator_type": "user",
    "reason": "用户购买虚拟道具（即时完成）",
    "metadata": {
      "sku_id": 401,
      "quantity": 1,
      "pay_amount": 500,
      "is_prop_order": true,
      "minted_item_id": 45255,
      "exchange_item_id": 535
    },
    "idempotency_key": "order_event_EM260613001231F2_completed_31_1781294786",
    "created_at": "2026-06-13 04:06:26"
  },
  {
    "event_id": "928",
    "order_no": "EM260615001289B4",
    "old_status": null,
    "new_status": "pending",
    "operator_id": 32,
    "operator_type": "user",
    "reason": "用户兑换商品",
    "metadata": {
      "sku_id": 6,
      "quantity": 1,
      "pay_amount": 10,
      "is_prop_order": false,
      "minted_item_id": 45268,
      "exchange_item_id": 6,
      "fulfillment_type": "physical"
    },
    "idempotency_key": "order_event_EM260615001289B4_pending_32_1781459177",
    "created_at": "2026-06-15 01:46:17"
  },
  {
    "event_id": "929",
    "order_no": "EM26061500129040",
    "old_status": null,
    "new_status": "pending",
    "operator_id": 32,
    "operator_type": "user",
    "reason": "用户兑换商品",
    "metadata": {
      "sku_id": 6,
      "quantity": 1,
      "pay_amount": 10,
      "is_prop_order": false,
      "minted_item_id": 45269,
      "exchange_item_id": 6,
      "fulfillment_type": "physical"
    },
    "idempotency_key": "order_event_EM26061500129040_pending_32_1781459828",
    "created_at": "2026-06-15 01:57:08"
  },
  {
    "event_id": "930",
    "order_no": "EM26061500129040",
    "old_status": "pending",
    "new_status": "approved",
    "operator_id": 32,
    "operator_type": "admin",
    "reason": "管理员审核通过",
    "metadata": null,
    "idempotency_key": "order_event_EM26061500129040_approved_32_1781460848",
    "created_at": "2026-06-15 02:14:08"
  },
  {
    "event_id": "932",
    "order_no": "EM26061500129040",
    "old_status": "approved",
    "new_status": "shipped",
    "operator_id": 32,
    "operator_type": "admin",
    "reason": "管理员变更状态为 shipped",
    "metadata": null,
    "idempotency_key": "order_event_EM26061500129040_shipped_32_1781460861",
    "created_at": "2026-06-15 02:14:21"
  },
  {
    "event_id": "933",
    "order_no": "EM260615001289B4",
    "old_status": "pending",
    "new_status": "approved",
    "operator_id": 32,
    "operator_type": "admin",
    "reason": "管理员审核通过",
    "metadata": null,
    "idempotency_key": "order_event_EM260615001289B4_approved_32_1781461480",
    "created_at": "2026-06-15 02:24:40"
  },
  {
    "event_id": "934",
    "order_no": "EM26061500129040",
    "old_status": "shipped",
    "new_status": "completed",
    "operator_id": 32,
    "operator_type": "admin",
    "reason": "管理员标记完成",
    "metadata": null,
    "idempotency_key": "order_event_EM26061500129040_completed_32_1781461523",
    "created_at": "2026-06-15 02:25:23"
  },
  {
    "event_id": "935",
    "order_no": "EM260621001291E7",
    "old_status": null,
    "new_status": "completed",
    "operator_id": 32,
    "operator_type": "user",
    "reason": "用户兑换商品（即时完成）",
    "metadata": {
      "sku_id": 499,
      "quantity": 1,
      "pay_amount": 100,
      "is_prop_order": false,
      "minted_item_id": 45382,
      "exchange_item_id": 627,
      "fulfillment_type": "voucher"
    },
    "idempotency_key": "order_event_EM260621001291E7_completed_32_1781992433",
    "created_at": "2026-06-21 05:53:53"
  },
  {
    "event_id": "936",
    "order_no": "EM26062100129243",
    "old_status": null,
    "new_status": "completed",
    "operator_id": 32,
    "operator_type": "user",
    "reason": "用户兑换商品（即时完成）",
    "metadata": {
      "sku_id": 499,
      "quantity": 1,
      "pay_amount": 100,
      "is_prop_order": false,
      "minted_item_id": 45383,
      "exchange_item_id": 627,
      "fulfillment_type": "voucher"
    },
    "idempotency_key": "order_event_EM26062100129243_completed_32_1781992478",
    "created_at": "2026-06-21 05:54:38"
  },
  {
    "event_id": "937",
    "order_no": "EM26062100129333",
    "old_status": null,
    "new_status": "completed",
    "operator_id": 32,
    "operator_type": "user",
    "reason": "用户兑换商品（即时完成）",
    "metadata": {
      "sku_id": 499,
      "quantity": 1,
      "pay_amount": 100,
      "is_prop_order": false,
      "minted_item_id": 45384,
      "exchange_item_id": 627,
      "fulfillment_type": "voucher"
    },
    "idempotency_key": "order_event_EM26062100129333_completed_32_1781992478",
    "created_at": "2026-06-21 05:54:38"
  },
  {
    "event_id": "938",
    "order_no": "EM26062200129464",
    "old_status": null,
    "new_status": "completed",
    "operator_id": 32,
    "operator_type": "user",
    "reason": "用户兑换商品（即时完成）",
    "metadata": {
      "sku_id": 402,
      "quantity": 1,
      "pay_amount": 1,
      "is_prop_order": true,
      "minted_item_id": 45448,
      "exchange_item_id": 536,
      "fulfillment_type": "virtual"
    },
    "idempotency_key": "order_event_EM26062200129464_completed_32_1782063381",
    "created_at": "2026-06-22 01:36:21"
  },
  {
    "event_id": "939",
    "order_no": "EM2606220012958B",
    "old_status": null,
    "new_status": "completed",
    "operator_id": 32,
    "operator_type": "user",
    "reason": "用户兑换商品（即时完成）",
    "metadata": {
      "sku_id": 402,
      "quantity": 1,
      "pay_amount": 1,
      "is_prop_order": true,
      "minted_item_id": 45449,
      "exchange_item_id": 536,
      "fulfillment_type": "virtual"
    },
    "idempotency_key": "order_event_EM2606220012958B_completed_32_1782065564",
    "created_at": "2026-06-22 02:12:44"
  }
]